feigen/__init__.py
feigen/_base.py
feigen/_version.py
feigen/bspline.py
feigen/bspline_texture.py
feigen/comm.py
feigen/custom_poisson2d.py
feigen/jacobian_determinant.py
feigen/log.py
feigen/nurbs_weights.py
feigen/poisson2d.py
feigen-0.0.7.dist-info/LICENSE
feigen-0.0.7.dist-info/METADATA
feigen-0.0.7.dist-info/WHEEL
feigen-0.0.7.dist-info/top_level.txt
feigen-0.0.7.dist-info/RECORD
