Metadata-Version: 2.1
Name: feigen
Version: 0.0.7
Summary: python interactive front-end for iganet.
Author-email: Jaewook Lee <jaewooklee042@gmail.com>, Matthias Möller <mmoelle1@gmail.com>
License: MPL 2.0
Keywords: iganet,interactive
Classifier: Development Status :: 2 - Pre-Alpha
Classifier: Intended Audience :: Science/Research
Classifier: Topic :: Scientific/Engineering :: Information Analysis
Classifier: License :: OSI Approved :: Mozilla Public License 2.0 (MPL 2.0)
Classifier: Operating System :: Microsoft :: Windows
Classifier: Operating System :: POSIX
Classifier: Operating System :: MacOS
Classifier: Programming Language :: Python :: 3.8
Classifier: Programming Language :: Python :: 3.9
Classifier: Programming Language :: Python :: 3.10
Classifier: Programming Language :: Python :: 3.11
Classifier: Programming Language :: Python :: 3.12
Requires-Python: >=3.7
License-File: LICENSE
Requires-Dist: vedo >=2024.5.1
Requires-Dist: numpy
Requires-Dist: gustaf >=0.0.23
Requires-Dist: splinepy[all] >=0.0.51
Requires-Dist: websockets
